risk_secret_provider/__init__.py
risk_secret_provider/my_secrets.py
risk_custom_secrets_provider-1.1.2.dist-info/METADATA
risk_custom_secrets_provider-1.1.2.dist-info/WHEEL
risk_custom_secrets_provider-1.1.2.dist-info/top_level.txt
risk_custom_secrets_provider-1.1.2.dist-info/RECORD
