Metadata-Version: 2.4
Name: risk-custom-secrets-provider
Version: 1.1.2
Requires-Dist: hvac==2.3.0
Requires-Dist: apache-airflow-providers-google==10.23.0
Requires-Dist: apache-airflow==2.9.3
Dynamic: requires-dist
